CHANGELOG.md
securecookies/__init__.py
securecookies/extras/__init__.py
securecookies/extras/csrf.py
securecookies/middleware.py
securecookies/py.typed
starlette_securecookies-1.1.1.dist-info/METADATA
starlette_securecookies-1.1.1.dist-info/WHEEL
starlette_securecookies-1.1.1.dist-info/licenses/LICENSE
starlette_securecookies-1.1.1.dist-info/RECORD
