Metadata-Version: 2.1
Name: starlette-securecookies
Version: 1.1.1
Summary: Secure cookie middleware for Starlette applications.
Keywords: starlette fastapi middleware encryption cookies
Home-page: https://securecookies.thearchitector.dev
Author-Email: Elias Gabriel <me@eliasfgabriel.com>
License: BSD 3-Clause License
Project-URL: Homepage, https://securecookies.thearchitector.dev
Project-URL: Documentation, https://securecookies.thearchitector.dev
Project-URL: Repository, https://github.com/thearchitector/starlette-securecookies
Project-URL: Changelog, https://github.com/thearchitector/starlette-securecookies/blob/main/CHANGELOG.md
Requires-Python: ~=3.7
Requires-Dist: starlette>=0.6.1
Requires-Dist: cryptography>=2.2
Requires-Dist: typing_extensions; python_version < "3.8"
Requires-Dist: starlette-csrf>=1.4.2; extra == "csrf"
Provides-Extra: csrf
